[
  {
    "path_prefix": "/acrobat-sign/docs",
    "timestamp": "2026-04-24T00:33:24.527Z",
    "status": "failed",
    "suite": "all"
  },
  {
    "path_prefix": "/adobe-pass",
    "timestamp": "2026-04-24T00:18:40.643Z",
    "status": "passed",
    "suite": "all"
  },
  {
    "path_prefix": "/cloud-storage",
    "timestamp": "2026-04-24T00:25:59.361Z",
    "status": "failed",
    "suite": "all"
  },
  {
    "path_prefix": "/commerce/testing",
    "timestamp": "2026-04-24T00:42:26.979Z",
    "status": "passed",
    "suite": "all"
  }
]